odoo9_addon_account_payment_purchase-9.0.1.0.0-py2.7-nspkg.pth
odoo9_addon_account_payment_purchase-9.0.1.0.0.dist-info/DESCRIPTION.rst
odoo9_addon_account_payment_purchase-9.0.1.0.0.dist-info/METADATA
odoo9_addon_account_payment_purchase-9.0.1.0.0.dist-info/RECORD
odoo9_addon_account_payment_purchase-9.0.1.0.0.dist-info/WHEEL
odoo9_addon_account_payment_purchase-9.0.1.0.0.dist-info/metadata.json
odoo9_addon_account_payment_purchase-9.0.1.0.0.dist-info/namespace_packages.txt
odoo9_addon_account_payment_purchase-9.0.1.0.0.dist-info/top_level.txt
odoo_addons/account_payment_purchase/README.rst
odoo_addons/account_payment_purchase/__init__.py
odoo_addons/account_payment_purchase/__openerp__.py
odoo_addons/account_payment_purchase/i18n/de.po
odoo_addons/account_payment_purchase/i18n/es.po
odoo_addons/account_payment_purchase/i18n/es_MX.po
odoo_addons/account_payment_purchase/i18n/fi.po
odoo_addons/account_payment_purchase/i18n/fr.po
odoo_addons/account_payment_purchase/i18n/fr_FR.po
odoo_addons/account_payment_purchase/i18n/hr.po
odoo_addons/account_payment_purchase/i18n/it.po
odoo_addons/account_payment_purchase/i18n/nl.po
odoo_addons/account_payment_purchase/i18n/pt_BR.po
odoo_addons/account_payment_purchase/i18n/pt_PT.po
odoo_addons/account_payment_purchase/i18n/sl.po
odoo_addons/account_payment_purchase/i18n/tr.po
odoo_addons/account_payment_purchase/i18n/tr_TR.po
odoo_addons/account_payment_purchase/i18n/zh_CN.po
odoo_addons/account_payment_purchase/models/__init__.py
odoo_addons/account_payment_purchase/models/account_invoice.py
odoo_addons/account_payment_purchase/models/procurement_order.py
odoo_addons/account_payment_purchase/models/purchase_order.py
odoo_addons/account_payment_purchase/static/description/icon.png
odoo_addons/account_payment_purchase/tests/__init__.py
odoo_addons/account_payment_purchase/tests/test_account_payment_purchase.py
odoo_addons/account_payment_purchase/views/purchase_order_view.xml
